hubspot_etl_pipeline_automatic_exporter/__init__.py
hubspot_etl_pipeline_automatic_exporter/exporter.py
hubspot_etl_pipeline_automatic_exporter-0.0.3.dist-info/METADATA
hubspot_etl_pipeline_automatic_exporter-0.0.3.dist-info/WHEEL
hubspot_etl_pipeline_automatic_exporter-0.0.3.dist-info/licenses/LICENSE
hubspot_etl_pipeline_automatic_exporter-0.0.3.dist-info/RECORD
